GeeksforgeeksDigitalElectronicsAndLogicDesignLectureNotes/README.md
GeeksforgeeksDigitalElectronicsAndLogicDesignLectureNotes/__init__.py
GeeksforgeeksDigitalElectronicsAndLogicDesignLectureNotes/__main__.py
GeeksforgeeksDigitalElectronicsAndLogicDesignLectureNotes/file.epub
GeeksforgeeksDigitalElectronicsAndLogicDesignLectureNotes/index.html
GeeksforgeeksDigitalElectronicsAndLogicDesignLectureNotes/css/__init__.py
GeeksforgeeksDigitalElectronicsAndLogicDesignLectureNotes/css/annotations.css
GeeksforgeeksDigitalElectronicsAndLogicDesignLectureNotes/css/main.css
GeeksforgeeksDigitalElectronicsAndLogicDesignLectureNotes/css/normalize.css
GeeksforgeeksDigitalElectronicsAndLogicDesignLectureNotes/css/popup.css
GeeksforgeeksDigitalElectronicsAndLogicDesignLectureNotes/font/__init__.py
GeeksforgeeksDigitalElectronicsAndLogicDesignLectureNotes/font/fontello.eot
GeeksforgeeksDigitalElectronicsAndLogicDesignLectureNotes/font/fontello.svg
GeeksforgeeksDigitalElectronicsAndLogicDesignLectureNotes/font/fontello.ttf
GeeksforgeeksDigitalElectronicsAndLogicDesignLectureNotes/font/fontello.woff
GeeksforgeeksDigitalElectronicsAndLogicDesignLectureNotes/img/__init__.py
GeeksforgeeksDigitalElectronicsAndLogicDesignLectureNotes/img/annotator-glyph-sprite.png
GeeksforgeeksDigitalElectronicsAndLogicDesignLectureNotes/img/annotator-icon-sprite.png
GeeksforgeeksDigitalElectronicsAndLogicDesignLectureNotes/img/apple-touch-icon.png
GeeksforgeeksDigitalElectronicsAndLogicDesignLectureNotes/img/cancelfullscreen.png
GeeksforgeeksDigitalElectronicsAndLogicDesignLectureNotes/img/close.png
GeeksforgeeksDigitalElectronicsAndLogicDesignLectureNotes/img/fullscreen.png
GeeksforgeeksDigitalElectronicsAndLogicDesignLectureNotes/img/loader.gif
GeeksforgeeksDigitalElectronicsAndLogicDesignLectureNotes/img/menu-icon.png
GeeksforgeeksDigitalElectronicsAndLogicDesignLectureNotes/img/save.png
GeeksforgeeksDigitalElectronicsAndLogicDesignLectureNotes/img/saved.png
geeksforgeeks_digital_electronics_and_logic_design_lecture_notes-2024.3.3.0.dist-info/METADATA
geeksforgeeks_digital_electronics_and_logic_design_lecture_notes-2024.3.3.0.dist-info/WHEEL
geeksforgeeks_digital_electronics_and_logic_design_lecture_notes-2024.3.3.0.dist-info/entry_points.txt
geeksforgeeks_digital_electronics_and_logic_design_lecture_notes-2024.3.3.0.dist-info/top_level.txt
geeksforgeeks_digital_electronics_and_logic_design_lecture_notes-2024.3.3.0.dist-info/RECORD
